fmo_core.cpython-313-x86_64-linux-gnu.so
fmo_core-0.10.dist-info/LICENSE
fmo_core-0.10.dist-info/METADATA
fmo_core-0.10.dist-info/WHEEL
fmo_core-0.10.dist-info/top_level.txt
fmo_core-0.10.dist-info/RECORD
